LICENSE.txt
MANIFEST.in
README.rst
setup.py
po_localization/__init__.py
po_localization/file_watcher.py
po_localization/middleware.py
po_localization/models.py
po_localization/parser.py
po_localization/po_file.py
po_localization/python_extractor.py
po_localization/strings.py
po_localization/template_extractor.py
po_localization/translations_loader.py
po_localization/translations_updater.py
po_localization/version.py
po_localization.egg-info/PKG-INFO
po_localization.egg-info/SOURCES.txt
po_localization.egg-info/dependency_links.txt
po_localization.egg-info/requires.txt
po_localization.egg-info/top_level.txt
po_localization/management/__init__.py
po_localization/management/commands/__init__.py
po_localization/management/commands/update_translations.py
po_localization/tests/__init__.py
po_localization/tests/sample.py
po_localization/tests/subtest.py
po_localization/tests/subtest_thunk.py
po_localization/tests/test_file_watcher.py
po_localization/tests/test_integration.py
po_localization/tests/test_parser.py
po_localization/tests/test_po_file.py
po_localization/tests/test_python_extractor.py
po_localization/tests/test_strings.py
po_localization/tests/test_template_extractor.py
po_localization/tests/test_app/__init__.py
po_localization/tests/test_app/apps.py
po_localization/tests/test_app/models.py
po_localization/tests/test_app/urls.py
po_localization/tests/test_app/views.py
po_localization/tests/test_project/__init__.py
po_localization/tests/test_project/urls.py
po_localization/tests/test_project/views.py