Metadata-Version: 1.1
Name: po-localization
Version: 0.5.3
Summary: Localize Django applications without compiling .po files
Home-page: https://github.com/kmichel/po-localization
Author: Kevin Michel
Author-email: kmichel.info@gmail.com
License: UNKNOWN
Download-URL: https://github.com/kmichel/po-localization/archive/v0.5.3.tar.gz
Keywords: django,localization
Platform: UNKNOWN
Classifier: Development Status :: 3 - Alpha
Classifier: Environment :: Web Environment
Classifier: Framework :: Django
Classifier: Intended Audience :: Developers
Classifier: License :: OSI Approved :: MIT License
Classifier: Operating System :: OS Independent
Classifier: Programming Language :: Python
Classifier: Programming Language :: Python :: 2
Classifier: Programming Language :: Python :: 2.7
Classifier: Programming Language :: Python :: 3
Classifier: Programming Language :: Python :: 3.2
Classifier: Programming Language :: Python :: 3.3
Classifier: Programming Language :: Python :: 3.4
Classifier: Topic :: Software Development :: Localization
Classifier: Topic :: Software Development :: Libraries :: Python Modules
